vedro_debug_prompt/__init__.py
vedro_debug_prompt/_debug_prompt.py
vedro_debug_prompt/_prompt_builder.py
vedro_debug_prompt/py.typed
vedro_debug_prompt-0.2.1.dist-info/licenses/LICENSE
vedro_debug_prompt-0.2.1.dist-info/METADATA
vedro_debug_prompt-0.2.1.dist-info/WHEEL
vedro_debug_prompt-0.2.1.dist-info/top_level.txt
vedro_debug_prompt-0.2.1.dist-info/RECORD
